{
  "Name": "NeuroKit2: The Python Toolbox for Neurophysiological Signal Processing",
  "DatasetDOI": "10.5281/zenodo.19613274",
  "Authors": ["Juan Moisés de la Serna Tuya", "Dominique Makowski"],
  "Description": "NeuroKit2 is an open-source Python toolbox designed for the comprehensive processing and analysis of neurophysiological signals (ECG, EEG, EDA, EMG, PPG). This distribution is part of a reproducibility initiative.",
  "License": "MIT",
  "Keywords": ["neurophysiology", "signal-processing", "reproducibility", "open-science"]
}
